.gitattributes
.gitignore
LICENSE.txt
run_all_tests.py
setup.cfg
setup.py
onyx/__init__.py
onyx.quantlib.egg-info/PKG-INFO
onyx.quantlib.egg-info/SOURCES.txt
onyx.quantlib.egg-info/dependency_links.txt
onyx.quantlib.egg-info/namespace_packages.txt
onyx.quantlib.egg-info/not-zip-safe
onyx.quantlib.egg-info/requires.txt
onyx.quantlib.egg-info/top_level.txt
onyx/quantlib/__init__.py
onyx/quantlib/black_scholes.py
onyx/quantlib/gabillon_g2f.py
onyx/quantlib/gbm_functions.py
onyx/quantlib/montecarlo_pricers.py
onyx/quantlib/tree_pricers.py
onyx/quantlib/test/__init__.py
onyx/quantlib/test/test_black_scholes.py
onyx/quantlib/test/test_gbm_functions.py
onyx/quantlib/test/test_montecarlo_pricers.py
onyx/quantlib/test/test_tree_pricers.py